pytest_eventlet/__init__.py
pytest_eventlet/plugin.py
pytest_eventlet-1.0.0.dist-info/LICENSE
pytest_eventlet-1.0.0.dist-info/METADATA
pytest_eventlet-1.0.0.dist-info/WHEEL
pytest_eventlet-1.0.0.dist-info/entry_points.txt
pytest_eventlet-1.0.0.dist-info/top_level.txt
pytest_eventlet-1.0.0.dist-info/zip-safe
pytest_eventlet-1.0.0.dist-info/RECORD
